cleantest/__init__.py
cleantest/_utils/__init__.py
cleantest/_utils/detect_os.py
cleantest/control/__init__.py
cleantest/control/configurator.py
cleantest/control/configure.py
cleantest/hooks/__init__.py
cleantest/hooks/startenv.py
cleantest/hooks/starttestlet.py
cleantest/hooks/stopenv.py
cleantest/hooks/stoptestlet.py
cleantest/hooks/data/__init__.py
cleantest/hooks/data/directory.py
cleantest/hooks/data/file.py
cleantest/meta/__init__.py
cleantest/meta/base_handler.py
cleantest/meta/base_package.py
cleantest/meta/cleantest_info.py
cleantest/meta/injectable.py
cleantest/pkg/__init__.py
cleantest/pkg/_base.py
cleantest/pkg/charmlib.py
cleantest/pkg/pip.py
cleantest/pkg/snap.py
cleantest/pkg/_mixins/__init__.py
cleantest/pkg/_mixins/snapd_support.py
cleantest/pkg/handler/__init__.py
cleantest/pkg/handler/snap_handler.py
cleantest/provider/__init__.py
cleantest/provider/local.py
cleantest/provider/lxd.py
cleantest/provider/_handler/__init__.py
cleantest/provider/_handler/base_handler.py
cleantest/provider/_handler/lxd_handler.py
cleantest/provider/data/__init__.py
cleantest/provider/data/env_data.py
cleantest/provider/data/lxd_data.py
cleantest/provider/data/_mixins/__init__.py
cleantest/provider/data/_mixins/dict_ops.py
cleantest/utils/__init__.py
cleantest/utils/detect_os.py
cleantest-0.3.0.dist-info/LICENSE
cleantest-0.3.0.dist-info/METADATA
cleantest-0.3.0.dist-info/WHEEL
cleantest-0.3.0.dist-info/top_level.txt
cleantest-0.3.0.dist-info/RECORD
