Metadata-Version: 2.1
Name: cleantest
Version: 0.3.0
Summary: Clean tests for developers in a hurry
Home-page: https://github.com/NucciTheBoss/cleantest
Author: Jason C. Nucciarone
Author-email: jason.nucciarone@canonical.com
License: Apache-2.0
Keywords: testing,framework,continuous integration
Classifier: Development Status :: 3 - Alpha
Classifier: Intended Audience :: Developers
Classifier: Intended Audience :: Science/Research
Classifier: License :: OSI Approved :: Apache Software License
Classifier: Operating System :: POSIX :: Linux
Classifier: Programming Language :: Python :: 3.6
Classifier: Programming Language :: Python :: 3.7
Classifier: Programming Language :: Python :: 3.8
Classifier: Programming Language :: Python :: 3.9
Classifier: Programming Language :: Python :: 3.10
Requires-Python: >=3.6
License-File: LICENSE
Requires-Dist: pylxd
